dssh/__init__.py
dssh/main.py
dssh-0.4.6.dist-info/METADATA
dssh-0.4.6.dist-info/WHEEL
dssh-0.4.6.dist-info/entry_points.txt
dssh-0.4.6.dist-info/RECORD
