Metadata-Version: 2.1
Name: dssh
Version: 0.4.6
Summary: SSH server manager on the basis of environments
Home-page: https://github.com/flutique/dssh
Keywords: ssh,ssh server
Author: Saurav Sharma
Maintainer: Saurav Sharma
Requires-Python: >=3.7.0,<4.0.0
Classifier: Programming Language :: Python :: 3
Classifier: Programming Language :: Python :: 3.7
Classifier: Programming Language :: Python :: 3.8
Classifier: Programming Language :: Python :: 3.9
Classifier: Programming Language :: Python :: 3.10
Classifier: Programming Language :: Python :: 3.11
Classifier: Programming Language :: Python :: 3.12
Requires-Dist: pexpect (>=4.9.0,<5.0.0)
Requires-Dist: prompt-toolkit (>=3.0.43,<4.0.0)
Requires-Dist: rich (>=13.7.0,<14.0.0)
Requires-Dist: typer (>=0.9.0,<0.10.0)
Project-URL: Bug Tracker, https://github.com/flutique/dssh/issues
Project-URL: Documentation, https://github.com/flutique/dssh
Project-URL: Repository, https://github.com/flutique/dssh
